cdslib/__init__.py
cdslib/core/__init__.py
cdslib/core/data/__init__.py
cdslib/core/data/chunked_memmap.py
cdslib/core/data/index_reader.py
cdslib/core/data/dataloader/__init__.py
cdslib/core/data/dataloader/batch_preparer.py
cdslib/core/data/dataloader/bucket_sampler.py
cdslib/core/data/dataloader/distributed_bucket_sampler.py
cdslib/core/data/dataloader/sort_sampler.py
cdslib/core/models/__init__.py
cdslib/core/models/base_model.py
cdslib/core/models/model_utils.py
cdslib/core/nn/__init__.py
cdslib/core/nn/nn_utils.py
cdslib/core/nn/functional/__init__.py
cdslib/core/nn/functional/upfirdn.py
cdslib/core/nn/modules/__init__.py
cdslib/core/nn/modules/attention.py
cdslib/core/nn/modules/conv.py
cdslib/core/nn/modules/filtered_conv.py
cdslib/core/nn/modules/focal_loss.py
cdslib/core/nn/modules/graves.py
cdslib/core/nn/modules/linear.py
cdslib/core/nn/modules/lstm.py
cdslib/core/nn/modules/nested_dropout.py
cdslib/core/nn/modules/subspace.py
cdslib/core/nn/modules/tacotron_content_encoder.py
cdslib/core/nn/modules/vrnn.py
cdslib/core/optim/__init__.py
cdslib/core/optim/optim_utils.py
cdslib/core/optim/tf_optim.py
cdslib/core/script/__init__.py
cdslib/core/script/base_train.py
cdslib/core/utils/__init__.py
cdslib/core/utils/argparse_utils.py
cdslib/core/utils/multigpu_utils.py
cdslib/core/utils/print_and_save.py
cdslib/core/utils/tensor_utils.py
plib/__init__.py
plib/mesh_utils.py
plib/metrics.py
plib/preprocess_obj.py
plib/render.py
plib/rigid_motion.py
plib/sample_utils.py
plib/spherical_gaussian.py
plib/utils.py
plib/uv_mapping.py
pointersect/__init__.py
pointersect/checkpoint/epoch700.pth
pointersect/data/__init__.py
pointersect/data/dataset_helper.py
pointersect/data/genlist.py
pointersect/data/hypersim_dataset.py
pointersect/data/mesh_dataset_v2.py
pointersect/inference/__init__.py
pointersect/inference/infer.py
pointersect/inference/inference_utils.py
pointersect/inference/main.py
pointersect/inference/structures.py
pointersect-0.0.1.dist-info/LICENSE
pointersect-0.0.1.dist-info/METADATA
pointersect-0.0.1.dist-info/WHEEL
pointersect-0.0.1.dist-info/entry_points.txt
pointersect-0.0.1.dist-info/top_level.txt
pointersect-0.0.1.dist-info/RECORD
