Metadata-Version: 2.1
Name: pointersect
Version: 0.0.1
Summary: Plug-and-play point-cloud rendering
Author-email: Rick Chang <jenhao_chang@apple.com>
License: Apple Sample Code
Requires-Python: >=3.7
License-File: LICENSE
Requires-Dist: chamferdist
Requires-Dist: fire
Requires-Dist: func-timeout
Requires-Dist: h5py
Requires-Dist: imageio
Requires-Dist: kornia
Requires-Dist: lpips
Requires-Dist: matplotlib
Requires-Dist: numpy
Requires-Dist: open3d
Requires-Dist: opencv-python
Requires-Dist: opencv-python-headless
Requires-Dist: Pillow
Requires-Dist: PyEXR
Requires-Dist: pygltflib
Requires-Dist: PyYAML
Requires-Dist: scikit-image
Requires-Dist: scipy
Requires-Dist: setuptools
Requires-Dist: tensorboard
Requires-Dist: tgt
Requires-Dist: torch
Requires-Dist: torch-scatter
Requires-Dist: tqdm
Requires-Dist: xatlas
